filetype_validator/__init__.py
filetype_validator-0.1.dist-info/LICENSE.txt
filetype_validator-0.1.dist-info/METADATA
filetype_validator-0.1.dist-info/WHEEL
filetype_validator-0.1.dist-info/top_level.txt
filetype_validator-0.1.dist-info/RECORD
