Metadata-Version: 2.1
Name: filetype-validator
Version: 0.1
Summary: # FILETYPE VALIDATOR
Requires-Dist: filetype
